deep_utils/__init__.py
deep_utils/audio/__init__.py
deep_utils/audio/asr/__init__.py
deep_utils/audio/asr/wav2vec2/__init__.py
deep_utils/audio/asr/wav2vec2/torch/__init__.py
deep_utils/audio/asr/wav2vec2/torch/main.py
deep_utils/audio/audio_utils/__init__.py
deep_utils/audio/audio_utils/librosa_utils.py
deep_utils/audio/audio_utils/soundfile_utils.py
deep_utils/audio/audio_utils/torchaudio_utils.py
deep_utils/audio/audio_utils/vox_utils.py
deep_utils/audio/classification/__init__.py
deep_utils/audio/classification/wav2vec2/__init__.py
deep_utils/audio/classification/wav2vec2/torch/__init__.py
deep_utils/audio/classification/wav2vec2/torch/audio_classification_wav2vec2.py
deep_utils/audio/diarization/__init__.py
deep_utils/audio/diarization/pyannote/__init__.py
deep_utils/audio/diarization/pyannote/pyannote_audio_diarization.py
deep_utils/audio/vad/__init__.py
deep_utils/audio/vad/pyannote/__init__.py
deep_utils/audio/vad/pyannote/pyannote_audio_vad.py
deep_utils/augmentation/__init__.py
deep_utils/augmentation/cutmix/__init__.py
deep_utils/augmentation/cutmix/cutmix_tf.py
deep_utils/augmentation/cutmix/cutmix_torch.py
deep_utils/augmentation/torch/__init__.py
deep_utils/augmentation/torch/augmentation_torch.py
deep_utils/blocks/__init__.py
deep_utils/blocks/tf/__init__.py
deep_utils/blocks/tf/blocks_tf.py
deep_utils/blocks/torch/__init__.py
deep_utils/blocks/torch/blocks_torch.py
deep_utils/callbacks/__init__.py
deep_utils/callbacks/tf_keras/__init__.py
deep_utils/callbacks/tf_keras/lr.py
deep_utils/callbacks/torch/__init__.py
deep_utils/callbacks/torch/torch_csv_logger.py
deep_utils/callbacks/torch/torch_model_checkpoint.py
deep_utils/callbacks/torch/torch_tensorboard.py
deep_utils/design_patterns/__init__.py
deep_utils/design_patterns/chain_of_responsibility/__init__.py
deep_utils/design_patterns/chain_of_responsibility/chain_of_responsibilities_handlers.py
deep_utils/dummy_objects/__init__.py
deep_utils/dummy_objects/dummies.py
deep_utils-1.5.15.dist-info/LICENSE
deep_utils-1.5.15.dist-info/METADATA
deep_utils-1.5.15.dist-info/WHEEL
deep_utils-1.5.15.dist-info/top_level.txt
deep_utils-1.5.15.dist-info/RECORD
