Metadata-Version: 2.1
Name: deep-utils
Version: 1.5.15
Summary: Deep Utils
Home-page: https://github.com/pooya-mohammadi/deep_utils
Author: Pooya Mohammadi Kazaj
Author-email: pooyamohammadikazaj@gmial.com
License: UNKNOWN
Download-URL: https://github.com/pooya-mohammadi/deep_utils/archive/refs/tags/1.5.15.tar.gz
Platform: UNKNOWN
Classifier: Programming Language :: Python :: 3
Classifier: License :: OSI Approved :: MIT License
Classifier: Operating System :: OS Independent
Requires-Python: >=3.6
Requires-Dist: numpy>=1.21.0
Requires-Dist: requests>=2.27.1
Requires-Dist: tqdm>=4.62.3
Provides-Extra: cv
Requires-Dist: opencv-python>=4.5.5.58; extra == "cv"
Provides-Extra: tf
Requires-Dist: tensorflow>=2.6.0; extra == "tf"
Requires-Dist: opencv-python>=4.5.5.58; extra == "tf"
Provides-Extra: torch
Requires-Dist: torch<1.12.0,>=1.8.0; extra == "torch"
Requires-Dist: torchvision>=0.10.0; extra == "torch"
Requires-Dist: torchaudio>=1.10.0; extra == "torch"
Provides-Extra: torch_transformers
Requires-Dist: torch<1.12.0,>=1.8.0; extra == "torch-transformers"
Requires-Dist: torchvision>=0.10.0; extra == "torch-transformers"
Requires-Dist: torchaudio>=1.10.0; extra == "torch-transformers"
Requires-Dist: transformers>=4.18.0; extra == "torch-transformers"
Provides-Extra: torchvision
Requires-Dist: torch<1.12.0,>=1.8.0; extra == "torchvision"
Requires-Dist: torchvision>=0.10.0; extra == "torchvision"
Requires-Dist: opencv-python>=4.5.5.58; extra == "torchvision"
